fastapi_offline/__init__.py
fastapi_offline/consts.py
fastapi_offline/core.py
fastapi_offline/py.typed
fastapi_offline/static/favicon.png
fastapi_offline/static/redoc.standalone.js
fastapi_offline/static/swagger-ui-bundle.js
fastapi_offline/static/swagger-ui.css
fastapi_offline-1.7.5.dist-info/licenses/LICENSE
fastapi_offline-1.7.5.dist-info/METADATA
fastapi_offline-1.7.5.dist-info/WHEEL
fastapi_offline-1.7.5.dist-info/top_level.txt
fastapi_offline-1.7.5.dist-info/RECORD
