Metadata-Version: 2.4
Name: fastapi_offline
Version: 1.7.5
Summary: FastAPI without reliance on CDNs for docs
Home-page: https://github.com/turettn/fastapi_offline
Author: Neal Turett
Author-email: turettn@gmail.com
License: MIT
Classifier: Programming Language :: Python :: 3
Classifier: Programming Language :: Python :: 3 :: Only
Requires-Python: >=3.8
License-File: LICENSE
Requires-Dist: fastapi>=0.99.0
Provides-Extra: test
Requires-Dist: pytest; extra == "test"
Requires-Dist: requests; extra == "test"
Requires-Dist: starlette[full]; extra == "test"
Dynamic: author
Dynamic: author-email
Dynamic: classifier
Dynamic: description
Dynamic: description-content-type
Dynamic: home-page
Dynamic: license
Dynamic: license-file
Dynamic: provides-extra
Dynamic: requires-dist
Dynamic: requires-python
Dynamic: summary
